athelas/__init__.py
athelas/__version__.py
athelas/cli.py
athelas/py.typed
athelas/knowledge/__init__.py
athelas/knowledge/connections/__init__.py
athelas/knowledge/demonstrations/__init__.py
athelas/knowledge/orchestrator/__init__.py
athelas/knowledge/retriever/__init__.py
athelas/models/__init__.py
athelas/models/actor_critic/__init__.py
athelas/models/bandit/__init__.py
athelas/models/lightgbm/__init__.py
athelas/models/lightgbmmt/__init__.py
athelas/models/lightgbmmt/lightgbmmt_inference.py
athelas/models/lightgbmmt/lightgbmmt_training.py
athelas/models/lightgbmmt/base/__init__.py
athelas/models/lightgbmmt/base/base_model.py
athelas/models/lightgbmmt/base/training_state.py
athelas/models/lightgbmmt/factory/__init__.py
athelas/models/lightgbmmt/factory/model_factory.py
athelas/models/lightgbmmt/hyperparams/__init__.py
athelas/models/lightgbmmt/hyperparams/hyperparameters_base.py
athelas/models/lightgbmmt/hyperparams/hyperparameters_lightgbmmt.py
athelas/models/lightgbmmt/implementations/__init__.py
athelas/models/lightgbmmt/implementations/mtgbm_model.py
athelas/models/lightgbmmt/loss/__init__.py
athelas/models/lightgbmmt/loss/adaptive_weight_loss.py
athelas/models/lightgbmmt/loss/base_loss_function.py
athelas/models/lightgbmmt/loss/fixed_weight_loss.py
athelas/models/lightgbmmt/loss/knowledge_distillation_loss.py
athelas/models/lightgbmmt/loss/loss_factory.py
athelas/models/lightgbmmt/loss/weight_strategies.py
athelas/models/lightgbmmt_legacy/__init__.py
athelas/models/lightgbmmt_legacy/run.py
athelas/models/lightgbmmt_legacy/setup.py
athelas/models/lightgbmmt_legacy/lightgbmmt/__init__.py
athelas/models/lightgbmmt_legacy/lightgbmmt/basic.py
athelas/models/lightgbmmt_legacy/lightgbmmt/callback.py
athelas/models/lightgbmmt_legacy/lightgbmmt/compat.py
athelas/models/lightgbmmt_legacy/lightgbmmt/engine.py
athelas/models/lightgbmmt_legacy/lightgbmmt/libpath.py
athelas/models/lightgbmmt_legacy/lightgbmmt/plotting.py
athelas-0.2.1.dist-info/licenses/LICENSE
athelas-0.2.1.dist-info/METADATA
athelas-0.2.1.dist-info/WHEEL
athelas-0.2.1.dist-info/entry_points.txt
athelas-0.2.1.dist-info/top_level.txt
athelas-0.2.1.dist-info/RECORD
