Metadata-Version: 2.4
Name: athelas
Version: 0.2.1
Summary: Zettelkasten-inspired ML model catalog with intelligent knowledge management
Author-email: Tianpei Xie <unidoctor@gmail.com>
License: MIT
Project-URL: Homepage, https://github.com/TianpeiLuke/athelas
Project-URL: Repository, https://github.com/TianpeiLuke/athelas
Project-URL: Documentation, https://github.com/TianpeiLuke/athelas/blob/main/README.md
Project-URL: Bug Tracker, https://github.com/TianpeiLuke/athelas/issues
Keywords: machine-learning,deep-learning,pytorch,knowledge-management,zettelkasten,model-catalog
Classifier: Development Status :: 3 - Alpha
Classifier: Intended Audience :: Developers
Classifier: Intended Audience :: Science/Research
Classifier: License :: OSI Approved :: MIT License
Classifier: Programming Language :: Python :: 3
Classifier: Programming Language :: Python :: 3.8
Classifier: Programming Language :: Python :: 3.9
Classifier: Programming Language :: Python :: 3.10
Classifier: Programming Language :: Python :: 3.11
Classifier: Topic :: Scientific/Engineering :: Artificial Intelligence
Classifier: Topic :: Software Development :: Libraries :: Python Modules
Requires-Python: >=3.8
License-File: LICENSE
Requires-Dist: torch>=2.0.0
Requires-Dist: pytorch-lightning>=2.0.0
Requires-Dist: lightning>=2.0.0
Requires-Dist: pydantic>=2.11.0
Requires-Dist: numpy>=1.26.0
Requires-Dist: pandas>=2.1.0
Requires-Dist: transformers>=4.30.0
Requires-Dist: beautifulsoup4>=4.12.0
Requires-Dist: gensim>=4.3.0
Requires-Dist: click>=8.2.0
Requires-Dist: typing_extensions>=4.14.0
Provides-Extra: aws
Requires-Dist: boto3>=1.39.0; extra == "aws"
Requires-Dist: botocore>=1.39.0; extra == "aws"
Requires-Dist: sagemaker>=2.248.0; extra == "aws"
Provides-Extra: boosting
Requires-Dist: xgboost>=2.0.0; extra == "boosting"
Requires-Dist: lightgbm>=3.0.0; extra == "boosting"
Provides-Extra: visualization
Requires-Dist: matplotlib>=3.8.0; extra == "visualization"
Requires-Dist: plotly>=5.0.0; extra == "visualization"
Requires-Dist: seaborn>=0.12.0; extra == "visualization"
Requires-Dist: pillow>=8.0.0; extra == "visualization"
Provides-Extra: deployment
Requires-Dist: onnx>=1.15.0; extra == "deployment"
Requires-Dist: onnxruntime>=1.16.0; extra == "deployment"
Requires-Dist: flask>=3.0.0; extra == "deployment"
Provides-Extra: jupyter
Requires-Dist: jupyter>=1.0.0; extra == "jupyter"
Requires-Dist: ipywidgets>=8.0.0; extra == "jupyter"
Requires-Dist: jupyterlab>=4.0.0; extra == "jupyter"
Requires-Dist: ipython>=8.0.0; extra == "jupyter"
Requires-Dist: nbformat>=5.0.0; extra == "jupyter"
Requires-Dist: jinja2>=3.0.0; extra == "jupyter"
Provides-Extra: dev
Requires-Dist: pytest>=7.0.0; extra == "dev"
Requires-Dist: pytest-cov>=4.0.0; extra == "dev"
Requires-Dist: pytest-mock>=3.10.0; extra == "dev"
Requires-Dist: black>=23.0.0; extra == "dev"
Requires-Dist: flake8>=6.0.0; extra == "dev"
Requires-Dist: isort>=5.0.0; extra == "dev"
Requires-Dist: mypy>=1.0.0; extra == "dev"
Requires-Dist: pre-commit>=3.0.0; extra == "dev"
Provides-Extra: all
Requires-Dist: athelas[aws,boosting,deployment,dev,jupyter,visualization]; extra == "all"
Dynamic: license-file
